Compiled from "ClassInit.java"
public class com.subei.classload.ClassInit extends java.lang.Object
  SourceFile: "ClassInit.java"
  minor version: 0
  major version: 50
  Constant pool:
const #1 = Method	#3.#12;	//  java/lang/Object."<init>":()V
const #2 = class	#13;	//  com/subei/classload/ClassInit
const #3 = class	#14;	//  java/lang/Object
const #4 = Asciz	<init>;
const #5 = Asciz	()V;
const #6 = Asciz	Code;
const #7 = Asciz	LineNumberTable;
const #8 = Asciz	main;
const #9 = Asciz	([Ljava/lang/String;)V;
const #10 = Asciz	SourceFile;
const #11 = Asciz	ClassInit.java;
const #12 = NameAndType	#4:#5;//  "<init>":()V
const #13 = Asciz	com/subei/classload/ClassInit;
const #14 = Asciz	java/lang/Object;

{
public com.subei.classload.ClassInit();
  Code:
   Stack=1, Locals=1, Args_size=1
   0:	aload_0
   1:	invokespecial	#1; //Method java/lang/Object."<init>":()V
   4:	return
  LineNumberTable: 
   line 13: 0


public static void main(java.lang.String[]);
  Code:
   Stack=1, Locals=2, Args_size=1
   0:	iconst_3
   1:	istore_1
   2:	return
  LineNumberTable: 
   line 26: 0
   line 32: 2


}

